flask_statgraph/__init__.py
flask_statgraph/utils.py
flask_statgraph/templates/flask_statistics_index.html
flask_statgraph/templates/flask_statistics_layout.html
flask_statgraph/templates/flask_statistics_single_view.html
flask_statgraph-1.0.3.dist-info/METADATA
flask_statgraph-1.0.3.dist-info/WHEEL
flask_statgraph-1.0.3.dist-info/licenses/LICENSE
flask_statgraph-1.0.3.dist-info/RECORD
