Metadata-Version: 2.3
Name: flask-statgraph
Version: 1.0.3
Summary: A package for displaying statistics for flask apps
Project-URL: Homepage, https://github.com/ephreal/flask-statgraph
Project-URL: Issues, https://github.com/ephreal/flask-statgraph/issues
Author-email: ephreal <contact@mylifeneeds.management>
License-File: LICENSE
Classifier: License :: OSI Approved :: MIT License
Classifier: Operating System :: OS Independent
Classifier: Programming Language :: Python :: 3
Requires-Python: >=3.8
Requires-Dist: flask
Requires-Dist: flask-sqlalchemy
